dispy/__init__.py
dispy/data/__init__.py
dispy/data/errors.py
dispy/data/intents.py
dispy/modules/__init__.py
dispy/modules/dictwrapper.py
dispy/modules/error.py
dispy/modules/eventargs.py
dispy/modules/heartbeats.py
dispy/modules/intents.py
dispy/modules/rest_api.py
dispy/modules/result.py
dispy/modules/appdirs/__init__.py
dispy/types/__init__.py
dispy/types/application.py
dispy/types/attachment.py
dispy/types/channel.py
dispy/types/component.py
dispy/types/embed.py
dispy/types/emoji.py
dispy/types/entitlement.py
dispy/types/guild.py
dispy/types/interaction.py
dispy/types/message.py
dispy/types/permissions.py
dispy/types/poll.py
dispy/types/reaction.py
dispy/types/role.py
dispy/types/stickers.py
dispy/types/team.py
dispy/types/thread.py
dispy/types/user.py
dispy/types/variable.py
dispy/types/t/__init__.py
dispy/types/t/application.py
dispy/types/t/attachment.py
dispy/types/t/channel.py
dispy/types/t/command.py
dispy/types/t/component.py
dispy/types/t/embed.py
dispy/types/t/emoji.py
dispy/types/t/entitlement.py
dispy/types/t/guild.py
dispy/types/t/interaction.py
dispy/types/t/message.py
dispy/types/t/permissions.py
dispy/types/t/poll.py
dispy/types/t/reaction.py
dispy/types/t/role.py
dispy/types/t/stickers.py
dispy/types/t/team.py
dispy/types/t/thread.py
dispy/types/t/user.py
dispy/types/t/variable.py
dispy_bot-0.1.1.dist-info/LICENSE
dispy_bot-0.1.1.dist-info/METADATA
dispy_bot-0.1.1.dist-info/WHEEL
dispy_bot-0.1.1.dist-info/top_level.txt
dispy_bot-0.1.1.dist-info/RECORD
