Metadata-Version: 2.2
Name: dispy-bot
Version: 0.1.1
Summary: A python-coded discord bot library.
Home-page: https://github.com/JamesMinoucha/Dispy
Author: James French
Author-email: James French <jamesfrench.contact@gmail.com>
License:                     GNU GENERAL PUBLIC LICENSE
Project-URL: Homepage, https://github.com/JamesMinoucha/Dispy
Project-URL: Issues, https://github.com/JamesMinoucha/Dispy/issues
Classifier: Development Status :: 4 - Beta
Classifier: Programming Language :: Python :: 3
Classifier: Programming Language :: Python :: 3.12
Classifier: License :: OSI Approved :: GNU General Public License v3 (GPLv3)
Classifier: Operating System :: OS Independent
Requires-Python: >=3.12
License-File: LICENSE
Requires-Dist: aiohttp>=3.11.11
Requires-Dist: setuptools>=75.6.0
Requires-Dist: websocket_client>=1.8.0
Dynamic: author
Dynamic: home-page
Dynamic: requires-python
